MANIFEST.in
README.md
setup.py
give_name_TP.egg-info/PKG-INFO
give_name_TP.egg-info/SOURCES.txt
give_name_TP.egg-info/dependency_links.txt
give_name_TP.egg-info/requires.txt
give_name_TP.egg-info/top_level.txt
my_names2_pac/__init__.py
my_names2_pac/my_names2.py