Metadata-Version: 2.1
Name: give-name-TP
Version: 1.0.0
Summary: Generate random names + their lenght
Home-page: UNKNOWN
License: UNKNOWN
Keywords: random names
Platform: UNKNOWN
